moreblocks/__init__.py
moreblocks/_modidx.py
moreblocks/attachments.py
moreblocks/blocks.py
moreblocks/core.py
moreblocks/elements.py
moreblocks/errors.py
moreblocks/messages.py
moreblocks/modals.py
moreblocks/objects.py
moreblocks/utils.py
moreblocks/views.py
moreblocks/rich_text/__init__.py
moreblocks/rich_text/elements.py
moreblocks/rich_text/objects.py
moreblocks-0.0.2.dist-info/licenses/LICENSE
moreblocks-0.0.2.dist-info/licenses/LICENSE.BSD-3-Clause
test/__init__.py
test/integration/__init__.py
test/integration/test_integration.py
test/unit/__init__.py
test/unit/test_attachments.py
test/unit/test_blocks.py
test/unit/test_elements.py
test/unit/test_errors.py
test/unit/test_messages.py
test/unit/test_objects.py
test/unit/test_rich_text.py
test/unit/test_utils.py
test/unit/test_views.py
test/unit/utils.py
moreblocks-0.0.2.dist-info/METADATA
moreblocks-0.0.2.dist-info/WHEEL
moreblocks-0.0.2.dist-info/entry_points.txt
moreblocks-0.0.2.dist-info/top_level.txt
moreblocks-0.0.2.dist-info/RECORD
